<?xml version="1.0"?>
<root>
    <page type="page">
        <pageID>5002</pageID>
        <name>Controller</name>
        <width>1280</width>
        <height>800</height>
        <button type="general">
            <bi>1</bi>
            <na>Background</na>
            <lt>12</lt>
            <tp>8</tp>
            <wt>1257</wt>
            <ht>667</ht>
            <zo>1</zo>
            <bs></bs>
            <rl>0</rl>
            <rh>255</rh>
            <ac di="0"/>
            <sr number="1">
                <bs>Single Line</bs>
                <cb>Black</cb>
                <cf>Grey1</cf>
                <ct>Black</ct>
                <ec>#000000FF</ec>
                <fi>20</fi>
            </sr>
            <sr number="2">
                <bs>Single Line</bs>
                <cb>Black</cb>
                <cf>Grey1</cf>
                <ct>Black</ct>
                <ec>#000000FF</ec>
                <fi>20</fi>
            </sr>
        </button>
        <button type="general">
            <bi>2</bi>
            <na>tabLogging</na>
            <lt>20</lt>
            <tp>20</tp>
            <wt>220</wt>
            <ht>50</ht>
            <zo>2</zo>
            <bs>Single Line</bs>
            <rl>0</rl>
            <rh>255</rh>
            <ac di="0"/>
            <pf type="stan">Logging</pf>
            <sr number="1">
                <bs>Single Line</bs>
                <cb>Black</cb>
                <cf>White</cf>
                <ct>Black</ct>
                <ec>#000000FF</ec>
                <fi>24</fi>
                <te>Logging</te>
            </sr>
            <sr number="2">
                <bs>Single Line</bs>
                <cb>Black</cb>
                <cf>White</cf>
                <ct>Black</ct>
                <ec>#000000FF</ec>
                <fi>539</fi>
                <te>Logging</te>
            </sr>
        </button>
        <button type="general">
            <bi>3</bi>
            <na>tabNetLinx</na>
            <lt>240</lt>
            <tp>20</tp>
            <wt>220</wt>
            <ht>50</ht>
            <zo>3</zo>
            <bs>Quad Line</bs>
            <rl>0</rl>
            <rh>255</rh>
            <ac di="0"/>
            <sr number="1">
                <bs>Quad Line</bs>
                <cb>Black</cb>
                <cf>White</cf>
                <ct>Black</ct>
                <ec>#000000FF</ec>
                <fi>539</fi>
                <te>NetLinx</te>
            </sr>
            <sr number="2">
                <bs>Quad Line</bs>
                <cb>Black</cb>
                <cf>White</cf>
                <ct>Black</ct>
                <ec>#000000FF</ec>
                <fi>24</fi>
                <te>NetLinx</te>
            </sr>
        </button>
        <button type="general">
            <bi>4</bi>
            <na>tabSIP</na>
            <lt>460</lt>
            <tp>20</tp>
            <wt>220</wt>
            <ht>50</ht>
            <zo>4</zo>
            <bs>Single Line</bs>
            <rl>0</rl>
            <rh>255</rh>
            <ac di="0"/>
            <pf type="stan">SIP</pf>
            <sr number="1">
                <bs>Single Line</bs>
                <cb>Black</cb>
                <cf>White</cf>
                <ct>Black</ct>
                <ec>#000000FF</ec>
                <fi>24</fi>
                <te>SIP</te>
            </sr>
            <sr number="2">
                <bs>Single Line</bs>
                <cb>Black</cb>
                <cf>White</cf>
                <ct>Black</ct>
                <ec>#000000FF</ec>
                <fi>24</fi>
                <te>SIP</te>
            </sr>
        </button>
        <button type="general">
            <bi>5</bi>
            <na>tabView</na>
            <lt>680</lt>
            <tp>20</tp>
            <wt>220</wt>
            <ht>50</ht>
            <zo>5</zo>
            <bs>Single Line</bs>
            <rl>0</rl>
            <rh>255</rh>
            <ac di="0"/>
            <pf type="stan">View</pf>
            <sr number="1">
                <bs>Single Line</bs>
                <cb>Black</cb>
                <cf>White</cf>
                <ct>Black</ct>
                <ec>#000000FF</ec>
                <fi>24</fi>
                <te>View</te>
            </sr>
            <sr number="2">
                <bs>Single Line</bs>
                <cb>Black</cb>
                <cf>White</cf>
                <ct>Black</ct>
                <ec>#000000FF</ec>
                <fi>24</fi>
                <te>View</te>
            </sr>
        </button>
        <button type="general">
            <bi>6</bi>
            <na>tabSound</na>
            <lt>900</lt>
            <tp>20</tp>
            <wt>220</wt>
            <ht>50</ht>
            <zo>6</zo>
            <bs>Single Line</bs>
            <rl>0</rl>
            <rh>255</rh>
            <ac di="0"/>
            <pf type="stan">Sound</pf>
            <sr number="1">
                <bs>Single Line</bs>
                <cb>Black</cb>
                <cf>White</cf>
                <ct>Black</ct>
                <ec>#000000FF</ec>
                <fi>24</fi>
                <te>Sound</te>
            </sr>
            <sr number="2">
                <bs>Single Line</bs>
                <cb>Black</cb>
                <cf>White</cf>
                <ct>Black</ct>
                <ec>#000000FF</ec>
                <fi>24</fi>
                <te>Sound</te>
            </sr>
        </button>
        <button type="general">
            <bi>7</bi>
            <na>btOK</na>
            <lt>850</lt>
            <tp>700</tp>
            <wt>160</wt>
            <ht>50</ht>
            <zo>7</zo>
            <bs></bs>
            <fb>momentary</fb>
            <ap>0</ap>
            <cp>0</cp>
            <ch>412</ch>
            <rl>0</rl>
            <rh>255</rh>
            <ac di="0"/>
            <sr number="1">
                <bs>AMX Elite Raised -M</bs>
                <cb>Black</cb>
                <cf>Grey3</cf>
                <ct>Black</ct>
                <ec>#000000FF</ec>
                <fi>24</fi>
                <te>OK</te>
            </sr>
            <sr number="2">
                <bs>AMX Elite Inset -M</bs>
                <cb>Black</cb>
                <cf>Grey3</cf>
                <ct>Black</ct>
                <ec>#000000FF</ec>
                <fi>24</fi>
                <te>OK</te>
            </sr>
        </button>
        <button type="general">
            <bi>8</bi>
            <na>btCancel</na>
            <lt>1026</lt>
            <tp>700</tp>
            <wt>160</wt>
            <ht>50</ht>
            <zo>8</zo>
            <bs></bs>
            <fb>momentary</fb>
            <ap>0</ap>
            <cp>0</cp>
            <ch>413</ch>
            <rl>0</rl>
            <rh>255</rh>
            <ac di="0"/>
            <sr number="1">
                <bs>AMX Elite Raised -M</bs>
                <cb>Black</cb>
                <cf>Grey3</cf>
                <ct>Black</ct>
                <ec>#000000FF</ec>
                <fi>24</fi>
                <te>Cancel</te>
            </sr>
            <sr number="2">
                <bs>AMX Elite Inset -M</bs>
                <cb>Black</cb>
                <cf>Grey3</cf>
                <ct>Black</ct>
                <ec>#000000FF</ec>
                <fi>24</fi>
                <te>Cancel</te>
            </sr>
        </button>
        <button type="general">
            <bi>9</bi>
            <na>lbNetLinx</na>
            <lt>40</lt>
            <tp>100</tp>
            <wt>200</wt>
            <ht>30</ht>
            <zo>9</zo>
            <bs></bs>
            <rl>0</rl>
            <rh>255</rh>
            <ac di="0"/>
            <sr number="1">
                <bs></bs>
                <cb>Black</cb>
                <cf>Transparent</cf>
                <ct>Black</ct>
                <ec>#000000FF</ec>
                <fi>21</fi>
                <te>NetLinx</te>
                <jt>4</jt>
            </sr>
            <sr number="2">
                <bs></bs>
                <cb>LightBlue</cb>
                <cf>White</cf>
                <ct>Black</ct>
                <ec>#000000FF</ec>
                <fi>21</fi>
                <te>NetLinx</te>
                <jt>4</jt>
            </sr>
        </button>
        <button type="general">
            <bi>10</bi>
            <na>lbNetworkPort</na>
            <lt>40</lt>
            <tp>140</tp>
            <wt>200</wt>
            <ht>30</ht>
            <zo>10</zo>
            <bs></bs>
            <rl>0</rl>
            <rh>255</rh>
            <ac di="0"/>
            <sr number="1">
                <bs></bs>
                <cb>Black</cb>
                <cf>Transparent</cf>
                <ct>Black</ct>
                <ec>#000000FF</ec>
                <fi>21</fi>
                <te>Network port</te>
                <jt>4</jt>
            </sr>
            <sr number="2">
                <bs></bs>
                <cb>LightBlue</cb>
                <cf>White</cf>
                <ct>Black</ct>
                <ec>#000000FF</ec>
                <fi>21</fi>
                <te>Network port</te>
                <jt>4</jt>
            </sr>
        </button>
        <button type="general">
            <bi>11</bi>
            <na>lbChannelNumber</na>
            <lt>40</lt>
            <tp>180</tp>
            <wt>200</wt>
            <ht>30</ht>
            <zo>11</zo>
            <bs></bs>
            <rl>0</rl>
            <rh>255</rh>
            <ac di="0"/>
            <sr number="1">
                <bs></bs>
                <cb>Black</cb>
                <cf>Transparent</cf>
                <ct>Black</ct>
                <ec>#000000FF</ec>
                <fi>21</fi>
                <te>Channel number</te>
                <jt>4</jt>
            </sr>
            <sr number="2">
                <bs></bs>
                <cb>LightBlue</cb>
                <cf>White</cf>
                <ct>Black</ct>
                <ec>#000000FF</ec>
                <fi>21</fi>
                <te>Channel number</te>
                <jt>4</jt>
            </sr>
        </button>
        <button type="general">
            <bi>12</bi>
            <na>lbPanelType</na>
            <lt>40</lt>
            <tp>220</tp>
            <wt>200</wt>
            <ht>30</ht>
            <zo>12</zo>
            <bs></bs>
            <rl>0</rl>
            <rh>255</rh>
            <ac di="0"/>
            <sr number="1">
                <bs></bs>
                <cb>Black</cb>
                <cf>Transparent</cf>
                <ct>Black</ct>
                <ec>#000000FF</ec>
                <fi>21</fi>
                <te>Panel type</te>
                <jt>4</jt>
            </sr>
            <sr number="2">
                <bs></bs>
                <cb>LightBlue</cb>
                <cf>White</cf>
                <ct>Black</ct>
                <ec>#000000FF</ec>
                <fi>21</fi>
                <te>Panel type</te>
                <jt>4</jt>
            </sr>
        </button>
        <button type="general">
            <bi>13</bi>
            <na>lbFTPuserName</na>
            <lt>40</lt>
            <tp>260</tp>
            <wt>200</wt>
            <ht>30</ht>
            <zo>13</zo>
            <bs></bs>
            <rl>0</rl>
            <rh>255</rh>
            <ac di="0"/>
            <sr number="1">
                <bs></bs>
                <cb>Black</cb>
                <cf>Transparent</cf>
                <ct>Black</ct>
                <ec>#000000FF</ec>
                <fi>21</fi>
                <te>FTP user name</te>
                <jt>4</jt>
            </sr>
            <sr number="2">
                <bs></bs>
                <cb>LightBlue</cb>
                <cf>White</cf>
                <ct>Black</ct>
                <ec>#000000FF</ec>
                <fi>21</fi>
                <te>FTP user name</te>
                <jt>4</jt>
            </sr>
        </button>
        <button type="general">
            <bi>14</bi>
            <na>lbFTPPassword</na>
            <lt>40</lt>
            <tp>300</tp>
            <wt>200</wt>
            <ht>30</ht>
            <zo>14</zo>
            <bs></bs>
            <rl>0</rl>
            <rh>255</rh>
            <ac di="0"/>
            <sr number="1">
                <bs></bs>
                <cb>Black</cb>
                <cf>Transparent</cf>
                <ct>Black</ct>
                <ec>#000000FF</ec>
                <fi>21</fi>
                <te>FTP password</te>
                <jt>4</jt>
            </sr>
            <sr number="2">
                <bs></bs>
                <cb>LightBlue</cb>
                <cf>White</cf>
                <ct>Black</ct>
                <ec>#000000FF</ec>
                <fi>21</fi>
                <te>FTP password</te>
                <jt>4</jt>
            </sr>
        </button>
        <button type="general">
            <bi>15</bi>
            <na>lbTP4fileName</na>
            <lt>40</lt>
            <tp>340</tp>
            <wt>200</wt>
            <ht>30</ht>
            <zo>15</zo>
            <bs></bs>
            <rl>0</rl>
            <rh>255</rh>
            <ac di="0"/>
            <sr number="1">
                <bs></bs>
                <cb>Black</cb>
                <cf>Transparent</cf>
                <ct>Black</ct>
                <ec>#000000FF</ec>
                <fi>21</fi>
                <te>TP4 file name</te>
                <jt>4</jt>
            </sr>
            <sr number="2">
                <bs></bs>
                <cb>LightBlue</cb>
                <cf>White</cf>
                <ct>Black</ct>
                <ec>#000000FF</ec>
                <fi>21</fi>
                <te>TP4 file name</te>
                <jt>4</jt>
            </sr>
        </button>
        <button type="general">
            <bi>16</bi>
            <na>lbFTPpassiveMode</na>
            <lt>40</lt>
            <tp>380</tp>
            <wt>200</wt>
            <ht>30</ht>
            <zo>16</zo>
            <bs></bs>
            <rl>0</rl>
            <rh>255</rh>
            <ac di="0"/>
            <sr number="1">
                <bs></bs>
                <cb>Black</cb>
                <cf>Transparent</cf>
                <ct>Black</ct>
                <ec>#000000FF</ec>
                <fi>21</fi>
                <te>FTP passive mode</te>
                <jt>4</jt>
            </sr>
            <sr number="2">
                <bs></bs>
                <cb>LightBlue</cb>
                <cf>White</cf>
                <ct>Black</ct>
                <ec>#000000FF</ec>
                <fi>21</fi>
                <te>FTP passive mode</te>
                <jt>4</jt>
            </sr>
        </button>
        <button type="textArea">
            <bi>17</bi>
            <na>txNetLinx</na>
            <lt>260</lt>
            <tp>100</tp>
            <wt>700</wt>
            <ht>30</ht>
            <zo>17</zo>
            <bs></bs>
            <ap>0</ap>
            <ad>122</ad>
            <cp>0</cp>
            <ac di="0"/>
            <sr number="1">
                <bs>Single Line</bs>
                <cb>Black</cb>
                <cf>White</cf>
                <ct>Black</ct>
                <ec>#000000FF</ec>
                <fi>21</fi>
            </sr>
            <sr number="2">
                <bs>Single Line</bs>
                <cb>Black</cb>
                <cf>White</cf>
                <ct>Black</ct>
                <ec>#000000FF</ec>
            </sr>
        </button>
        <button type="textArea">
            <bi>18</bi>
            <na>txNetworkPort</na>
            <lt>260</lt>
            <tp>140</tp>
            <wt>150</wt>
            <ht>30</ht>
            <zo>18</zo>
            <bs></bs>
            <ap>0</ap>
            <ad>124</ad>
            <cp>0</cp>
            <ac di="0"/>
            <sr number="1">
                <bs>Single Line</bs>
                <cb>Black</cb>
                <cf>White</cf>
                <ct>Black</ct>
                <ec>#000000FF</ec>
                <fi>21</fi>
            </sr>
            <sr number="2">
                <bs>Single Line</bs>
                <cb>Black</cb>
                <cf>White</cf>
                <ct>Black</ct>
                <ec>#000000FF</ec>
            </sr>
        </button>
        <button type="textArea">
            <bi>19</bi>
            <na>txChannelNumber</na>
            <lt>260</lt>
            <tp>180</tp>
            <wt>150</wt>
            <ht>30</ht>
            <zo>19</zo>
            <bs></bs>
            <ap>0</ap>
            <ad>123</ad>
            <cp>0</cp>
            <ac di="0"/>
            <sr number="1">
                <bs>Single Line</bs>
                <cb>Black</cb>
                <cf>White</cf>
                <ct>Black</ct>
                <ec>#000000FF</ec>
                <fi>21</fi>
            </sr>
            <sr number="2">
                <bs>Single Line</bs>
                <cb>Black</cb>
                <cf>White</cf>
                <ct>Black</ct>
                <ec>#000000FF</ec>
            </sr>
        </button>
        <button type="textArea">
            <bi>20</bi>
            <na>txPanelType</na>
            <lt>260</lt>
            <tp>220</tp>
            <wt>700</wt>
            <ht>30</ht>
            <zo>20</zo>
            <bs></bs>
            <ap>0</ap>
            <ad>199</ad>
            <cp>0</cp>
            <ac di="0"/>
            <sr number="1">
                <bs>Single Line</bs>
                <cb>Black</cb>
                <cf>White</cf>
                <ct>Black</ct>
                <ec>#000000FF</ec>
                <fi>21</fi>
            </sr>
            <sr number="2">
                <bs>Single Line</bs>
                <cb>Black</cb>
                <cf>White</cf>
                <ct>Black</ct>
                <ec>#000000FF</ec>
            </sr>
        </button>
        <button type="textArea">
            <bi>21</bi>
            <na>txFtpUserName</na>
            <lt>260</lt>
            <tp>260</tp>
            <wt>700</wt>
            <ht>30</ht>
            <zo>21</zo>
            <bs></bs>
            <ap>0</ap>
            <cp>0</cp>
            <ad>2020</ad>
            <ch>2020</ch>
            <ac di="0"/>
            <sr number="1">
                <bs>Single Line</bs>
                <cb>Black</cb>
                <cf>White</cf>
                <ct>Black</ct>
                <ec>#000000FF</ec>
                <fi>21</fi>
            </sr>
            <sr number="2">
                <bs>Single Line</bs>
                <cb>Black</cb>
                <cf>White</cf>
                <ct>Black</ct>
                <ec>#000000FF</ec>
            </sr>
        </button>
        <button type="textArea">
            <bi>22</bi>
            <na>txFtpPassword</na>
            <lt>260</lt>
            <tp>300</tp>
            <wt>700</wt>
            <ht>30</ht>
            <zo>22</zo>
            <bs></bs>
            <ap>0</ap>
            <ad>2021</ad>
            <ch>2021</ch>
            <pc>*</pc>
            <ac di="0"/>
            <sr number="1">
                <bs>Single Line</bs>
                <cb>Black</cb>
                <cf>White</cf>
                <ct>Black</ct>
                <ec>#000000FF</ec>
                <fi>21</fi>
            </sr>
            <sr number="2">
                <bs>Single Line</bs>
                <cb>Black</cb>
                <cf>White</cf>
                <ct>Black</ct>
                <ec>#000000FF</ec>
            </sr>
        </button>
        <button type="textArea">
            <bi>23</bi>
            <na>txTP4FileName</na>
            <lt>260</lt>
            <tp>340</tp>
            <wt>605</wt>
            <ht>30</ht>
            <zo>23</zo>
            <bs></bs>
            <ap>0</ap>
            <ad>25</ad>
            <ac di="0"/>
            <sr number="1">
                <bs>Single Line</bs>
                <cb>Black</cb>
                <cf>White</cf>
                <ct>Black</ct>
                <ec>#000000FF</ec>
                <fi>21</fi>
            </sr>
            <sr number="2">
                <bs>Single Line</bs>
                <cb>Black</cb>
                <cf>White</cf>
                <ct>Black</ct>
                <ec>#000000FF</ec>
            </sr>
        </button>
        <button type="general">
            <bi>24</bi>
            <na>btCbTP4FileName</na>
            <lt>864</lt>
            <tp>340</tp>
            <wt>20</wt>
            <ht>30</ht>
            <zo>24</zo>
            <bs></bs>
            <rl>0</rl>
            <rh>255</rh>
            <ac di="0"/>
            <pf type="sToggle">TP4FileName</pf>
            <sr number="1">
                <bs>Single Line</bs>
                <cb>Black</cb>
                <cf>White</cf>
                <ct>Black</ct>
                <ec>#000000FF</ec>
                <fi>532</fi>
                <te>Z</te>
            </sr>
            <sr number="2">
                <bs>Single Line</bs>
                <cb>Black</cb>
                <cf>White</cf>
                <ct>Black</ct>
                <ec>#000000FF</ec>
                <fi>532</fi>
                <te>Z</te>
            </sr>
        </button>
        <button type="general">
            <bi>25</bi>
            <na>cbPassiv</na>
            <lt>260</lt>
            <tp>380</tp>
            <wt>30</wt>
            <ht>30</ht>
            <zo>25</zo>
            <bs></bs>
            <ap>0</ap>
            <cp>0</cp>
            <ch>2031</ch>
            <rl>0</rl>
            <rh>255</rh>
            <ac di="0"/>
            <sr number="1">
                <bs>Single Line</bs>
                <cb>Black</cb>
                <cf>White</cf>
                <ct>Black</ct>
                <ec>#000000FF</ec>
                <fi>537</fi>
            </sr>
            <sr number="2">
                <bs>Single Line</bs>
                <cb>Black</cb>
                <cf>White</cf>
                <ct>Black</ct>
                <ec>#000000FF</ec>
                <fi>537</fi>
                <te>a</te>
            </sr>
        </button>
        <button type="general">
            <bi>26</bi>
            <na>lbPassiv</na>
            <lt>305</lt>
            <tp>380</tp>
            <wt>74</wt>
            <ht>30</ht>
            <zo>26</zo>
            <bs></bs>
            <rl>0</rl>
            <rh>255</rh>
            <ac di="0"/>
            <sr number="1">
                <bs></bs>
                <cb>Black</cb>
                <cf>Transparent</cf>
                <ct>Black</ct>
                <ec>#000000FF</ec>
                <fi>21</fi>
                <te>Passiv</te>
                <jt>4</jt>
            </sr>
            <sr number="2">
                <bs></bs>
                <cb>LightBlue</cb>
                <cf>White</cf>
                <ct>Black</ct>
                <ec>#000000FF</ec>
                <fi>21</fi>
                <te>Passiv</te>
                <jt>4</jt>
            </sr>
        </button>
        <button type="general">
            <bi>27</bi>
            <na>btDownload</na>
            <lt>902</lt>
            <tp>340</tp>
            <wt>58</wt>
            <ht>30</ht>
            <zo>27</zo>
            <bs></bs>
            <ap>0</ap>
			<cp>0</cp>
            <ch>2030</ch>
            <rl>0</rl>
            <rh>255</rh>
            <ac di="0"/>
            <sr number="1">
                <bs></bs>
                <cb>VeryLightYellow</cb>
                <cf>Transparent</cf>
                <ct>Black</ct>
                <ec>#000000FF</ec>
                <bm>setup_download_green.png</bm>
                <fi>20</fi>
            </sr>
            <sr number="2">
                <bs></bs>
                <cb>LightBlue</cb>
                <cf>Transparent</cf>
                <ct>Black</ct>
                <ec>#000000FF</ec>
                <bm>setup_download_red.png</bm>
                <fi>20</fi>
            </sr>
        </button>
        <sr number="1">
            <bs></bs>
            <cb></cb>
            <cf>White</cf>
            <ct>Black</ct>
            <ec>#000000FF</ec>
            <fi>20</fi>
        </sr>
    </page>
</root>
